fal_client/__init__.py
fal_client/auth.py
fal_client/client.py
fal_client/py.typed
fal_client-0.11.0.dist-info/METADATA
fal_client-0.11.0.dist-info/WHEEL
fal_client-0.11.0.dist-info/top_level.txt
fal_client-0.11.0.dist-info/RECORD
