Metadata-Version: 2.4
Name: fal_client
Version: 0.11.0
Summary: Python client for fal.ai
Author: Features & Labels <support@fal.ai>
Project-URL: homepage, https://fal.ai
Project-URL: repository, https://github.com/fal-ai/fal
Requires-Python: >=3.8
Requires-Dist: httpx<1,>=0.21.0
Requires-Dist: httpx-sse<0.5,>=0.4.0
Requires-Dist: msgpack<2,>=1.0.7
Requires-Dist: websockets>=12.0
Provides-Extra: docs
Requires-Dist: sphinx; extra == "docs"
Requires-Dist: sphinx-rtd-theme; extra == "docs"
Requires-Dist: sphinx-autodoc-typehints; extra == "docs"
Provides-Extra: test
Requires-Dist: pytest; extra == "test"
Requires-Dist: pytest-asyncio; extra == "test"
Requires-Dist: pytest-mock; extra == "test"
Requires-Dist: pillow; extra == "test"
Provides-Extra: dev
Requires-Dist: fal_client[docs,test]; extra == "dev"
